geo_tool/__init__.py
geo_tool/baidu_geo.py
geo_tool/base_geo.py
geo_tool/gaode_geo.py
geo_tool/geo_transform.py
geo_tool/google_geo.py
geo_tool-1.1.2.dist-info/METADATA
geo_tool-1.1.2.dist-info/WHEEL
geo_tool-1.1.2.dist-info/top_level.txt
geo_tool-1.1.2.dist-info/RECORD
