Metadata-Version: 2.1
Name: geo-tool
Version: 1.1.2
Summary: 经纬度解析转换工具(Geographic location analysis and conversion tool)
Home-page: UNKNOWN
Author: abo123456
Author-email: abcdef123456chen@sohu.com
Maintainer: abo123456
Maintainer-email: abcdef123456chen@sohu.com
License: MIT License
Keywords: detool,decorators
Platform: all
Classifier: Development Status :: 4 - Beta
Classifier: Operating System :: OS Independent
Classifier: Intended Audience :: Developers
Classifier: License :: OSI Approved :: MIT License
Classifier: Programming Language :: Python
Classifier: Programming Language :: Python :: Implementation
Classifier: Programming Language :: Python :: 3.6
Classifier: Programming Language :: Python :: 3.7
Classifier: Programming Language :: Python :: 3.8
Classifier: Programming Language :: Python :: 3.9
Classifier: Programming Language :: Python :: 3.10
Classifier: Topic :: Software Development :: Libraries
Requires-Dist: requests (>=2.22.0)
Requires-Dist: geocoder (>=1.38.1)
Requires-Dist: googlemaps (>=4.4.1)
Requires-Dist: loguru (>=0.3.2)
